growstocks/__init__.py
growstocks/client.py
growstocks/errors.py
growstocks/py.typed
growstocks/scopes.py
growstocks/transaction.py
growstocks/user.py
growstocks/wrapper.py
growstocks/aio/__init__.py
growstocks/aio/client.py
growstocks/types/__init__.py
growstocks/types/client.py
growstocks/types/transaction.py
growstocks/types/user.py
growstocks-1.2.1.dist-info/LICENSE
growstocks-1.2.1.dist-info/METADATA
growstocks-1.2.1.dist-info/WHEEL
growstocks-1.2.1.dist-info/top_level.txt
growstocks-1.2.1.dist-info/RECORD
