Metadata-Version: 2.1
Name: growstocks
Version: 1.2.1
Summary: A wrapper for the GrowStocks API, made for both synchronous and asynchronous applications.
Home-page: https://github.com/BobDotCom/growstocks
Author: BobDotCom
Author-email: bobdotcomgt@gmail.com
License: MIT
Download-URL: https://github.com/BobDotCom/growstocks/releases
Project-URL: Documentation, https://growstocks.readthedocs.io/en/latest/index.html
Project-URL: Source, https://github.com/BobDotCom/growstocks
Project-URL: Tracker, https://github.com/BobDotCom/growstocks/issues
Platform: UNKNOWN
Classifier: Development Status :: 5 - Production/Stable
Classifier: License :: OSI Approved :: MIT License
Classifier: Intended Audience :: Developers
Classifier: Natural Language :: English
Classifier: Operating System :: OS Independent
Classifier: Programming Language :: Python :: 3.6
Classifier: Programming Language :: Python :: 3.7
Classifier: Programming Language :: Python :: 3.8
Classifier: Programming Language :: Python :: 3.9
Classifier: Programming Language :: Python :: 3.10
Classifier: Topic :: Software Development :: Libraries
Classifier: Topic :: Software Development :: Libraries :: Python Modules
Classifier: Topic :: Utilities
Classifier: Typing :: Typed
Requires-Python: >=3.6
License-File: LICENSE
Requires-Dist: requests
Requires-Dist: urllib3
Requires-Dist: aiohttp
